{"stats":{"minecraft:dropped":{"minecraft:wheat_seeds":4},"minecraft:used":{"minecraft:water_bucket":27,"minecraft:bread":3,"minecraft:bucket":27,"minecraft:beetroot_soup":1},"minecraft:picked_up":{"minecraft:beetroot":4,"minecraft:beetroot_seeds":14,"minecraft:wheat_seeds":7,"minecraft:bucket":1,"minecraft:bread":17,"minecraft:cobblestone":1},"minecraft:custom":{"minecraft:open_barrel":1,"minecraft:time_since_rest":6098,"minecraft:open_chest":11,"minecraft:crouch_one_cm":1689,"minecraft:play_time":15244,"minecraft:sprint_one_cm":107599,"minecraft:damage_taken":250,"minecraft:walk_one_cm":31818,"minecraft:sneak_time":478,"minecraft:walk_under_water_one_cm":746,"minecraft:drop":4,"minecraft:jump":354,"minecraft:damage_dealt":16,"minecraft:leave_game":1,"minecraft:time_since_death":15244,"minecraft:walk_on_water_one_cm":1060,"minecraft:sleep_in_bed":6,"minecraft:total_world_time":15244,"minecraft:climb_one_cm":2772,"minecraft:interact_with_crafting_table":1,"minecraft:fall_one_cm":9109,"minecraft:fly_one_cm":58158}},"DataVersion":3700}